seclm/__init__.py
seclm/ssl/__init__.py
seclm/ssl/context.py
seclm-0.1.1.dist-info/METADATA
seclm-0.1.1.dist-info/WHEEL
seclm-0.1.1.dist-info/top_level.txt
seclm-0.1.1.dist-info/RECORD
