Metadata-Version: 2.1
Name: seclm
Version: 0.1.1
Summary: seclm
Home-page: https://github.com/sec-lm/seclm
Author: stneng
Author-email: git@stneng.com
Requires-Python: >=3.10
Requires-Dist: cryptography
